fetch_data/__init__.py
fetch_data/_version.py
fetch_data/catalog.py
fetch_data/core.py
fetch_data/utils.py
tests/__init__.py
tests/test_download.py
fetch_data-0.2.5.2.dist-info/LICENSE.txt
fetch_data-0.2.5.2.dist-info/METADATA
fetch_data-0.2.5.2.dist-info/WHEEL
fetch_data-0.2.5.2.dist-info/top_level.txt
fetch_data-0.2.5.2.dist-info/RECORD
