Metadata-Version: 2.1
Name: fetch-data
Version: 0.2.5.2
Summary: Download remote data (HTTP, FTP, SFTP) and store locally for data pipeline
Home-page: https://github.com/lukegre/fetch-data
Author: Luke Gregor
Author-email: AUTHOR@EMAIL.COM
License: MIT
Platform: UNKNOWN
Classifier: Development Status :: 5 - Production/Stable
Classifier: Topic :: Scientific/Engineering
Classifier: Intended Audience :: Science/Research
Classifier: Operating System :: OS Independent
Classifier: Programming Language :: Python
Classifier: Programming Language :: Python :: 3
Classifier: Programming Language :: Python :: 3.6
Classifier: Programming Language :: Python :: 3.7
Classifier: Programming Language :: Python :: 3.8
Classifier: License :: OSI Approved :: MIT License
Requires-Python: >=3.6
License-File: LICENSE.txt
